slfl/__init__.py
slfl/__main__.py
slfl/_cli.py
slfl/_dsl.py
slfl/engine/__init__.py
slfl/engine/_memory.py
slfl/engine/_runner.py
slfl/engine/_traversal.py
slfl/engine/_types.py
slfl-0.2.0.dist-info/METADATA
slfl-0.2.0.dist-info/WHEEL
slfl-0.2.0.dist-info/entry_points.txt
slfl-0.2.0.dist-info/licenses/LICENSE
slfl-0.2.0.dist-info/RECORD
